LICENSE
README
setup.py
cptec_model.egg-info/PKG-INFO
cptec_model.egg-info/SOURCES.txt
cptec_model.egg-info/dependency_links.txt
cptec_model.egg-info/requires.txt
cptec_model.egg-info/top_level.txt
cptecmodel/CPTEC_BAM.py
cptecmodel/CPTEC_BRAMS.py
cptecmodel/CPTEC_ETA.py
cptecmodel/CPTEC_GFS.py
cptecmodel/CPTEC_UTIL.py
cptecmodel/CPTEC_WRF.py
cptecmodel/CPTEC_Widgets.py
cptecmodel/Stats.py
cptecmodel/_dict_bam.py
cptecmodel/_dict_brams.py
cptecmodel/_dict_eta.py
cptecmodel/_dict_gfs.py
cptecmodel/_dict_wrf.py
cptecmodel/_version.py