Metadata-Version: 2.1
Name: cptec-model
Version: 0.1.11
Summary: Módulo para distribuição de Modelos Numéricos.
Home-page: https://cptec-model.readthedocs.io/en/latest/
Author: Framework
Author-email: frameworkcptec@gmail.com
License: MIT
Project-URL: Código fonte, https://github.com/framework-CPTEC/CPTEC-user
Project-URL: Download, https://github.com/framework-CPTEC/CPTEC-user
Keywords: recuperação de dados modelos numericos CPTEC INPE
Classifier: Development Status :: 5 - Production/Stable
Classifier: Intended Audience :: Developers
Classifier: License :: OSI Approved :: MIT License
Classifier: Natural Language :: Portuguese (Brazilian)
Classifier: Operating System :: OS Independent
Classifier: Topic :: Software Development :: Internationalization
Classifier: Topic :: Scientific/Engineering :: Physics
Requires-Python: >=3.10
License-File: LICENSE
Requires-Dist: numpy
Requires-Dist: pandas
Requires-Dist: matplotlib
Requires-Dist: pycurl
Requires-Dist: cfgrib
Requires-Dist: netCDF4
Requires-Dist: xarray
Requires-Dist: dask
Requires-Dist: scipy
Requires-Dist: xesmf
